cnn_candlestick_patterns_detector/__init__.py
cnn_candlestick_patterns_detector/GAN/__init__.py
cnn_candlestick_patterns_detector/GAN/generator_trainer.py
cnn_candlestick_patterns_detector/GAN/architecture/__init__.py
cnn_candlestick_patterns_detector/GAN/architecture/generator_7.py
cnn_candlestick_patterns_detector/GAN/data_provider/__init__.py
cnn_candlestick_patterns_detector/GAN/data_provider/discriminator_data_provider.py
cnn_candlestick_patterns_detector/config/__init__.py
cnn_candlestick_patterns_detector/config/logger_config.py
cnn_candlestick_patterns_detector/environment/__init__.py
cnn_candlestick_patterns_detector/environment/model_tester.py
cnn_candlestick_patterns_detector/environment/model_trainer.py
cnn_candlestick_patterns_detector/forest_classifier/__init__.py
cnn_candlestick_patterns_detector/forest_classifier/group_homogeneity_analyzer.py
cnn_candlestick_patterns_detector/forest_classifier/model_homogeneity_estimator.py
cnn_candlestick_patterns_detector/forest_classifier/train_cat_boost_classifier.py
cnn_candlestick_patterns_detector/forest_classifier/train_random_forest_classifier.py
cnn_candlestick_patterns_detector/preprocessing/__init__.py
cnn_candlestick_patterns_detector/preprocessing/candlestick_series_chart_generator.py
cnn_candlestick_patterns_detector/preprocessing/candlestick_series_normalizer.py
cnn_candlestick_patterns_detector/preprocessing/cnn_soft_labels_dataset_checker.py
cnn_candlestick_patterns_detector/preprocessing/dataset_archive_operations.py
cnn_candlestick_patterns_detector/preprocessing/dataset_calculations.py
cnn_candlestick_patterns_detector/preprocessing/dataset_files_mover.py
cnn_candlestick_patterns_detector/preprocessing/dataset_fixes.py
cnn_candlestick_patterns_detector/preprocessing/dataset_orginizer.py
cnn_candlestick_patterns_detector/preprocessing/dataset_probabiliry_grouper.py
cnn_candlestick_patterns_detector/preprocessing/dataset_randomizing.py
cnn_candlestick_patterns_detector-0.1.8.dist-info/METADATA
cnn_candlestick_patterns_detector-0.1.8.dist-info/WHEEL
cnn_candlestick_patterns_detector-0.1.8.dist-info/top_level.txt
cnn_candlestick_patterns_detector-0.1.8.dist-info/RECORD
