Metadata-Version: 2.1
Name: cnn_candlestick_patterns_detector
Version: 0.1.8
Summary: CNN classifier for candlestick patterns size 7
Author: Maksym Usanin
Author-email: usanin.max@gmail.com
Classifier: Programming Language :: Python :: 3
Classifier: Programming Language :: Python :: 3.11
Classifier: Operating System :: OS Independent
Requires-Python: >=3.11
Requires-Dist: torch
Requires-Dist: numpy
